tinycss2/__init__.py
tinycss2/ast.py
tinycss2/bytes.py
tinycss2/color3.py
tinycss2/nth.py
tinycss2/parser.py
tinycss2/serializer.py
tinycss2/tokenizer.py
tinycss2-1.2.0.dist-info/LICENSE
tinycss2-1.2.0.dist-info/WHEEL
tinycss2-1.2.0.dist-info/METADATA
tinycss2-1.2.0.dist-info/RECORD
