Metadata-Version: 2.1
Name: tinycss2
Version: 1.2.0
Summary: A tiny CSS parser
Keywords: css,parser
Author-email: Simon Sapin <simon.sapin@exyr.org>
Maintainer-email: CourtBouillon <contact@courtbouillon.org>
Requires-Python: >=3.7
Classifier: Development Status :: 5 - Production/Stable
Classifier: Intended Audience :: Developers
Classifier: License :: OSI Approved :: BSD License
Classifier: Operating System :: OS Independent
Classifier: Programming Language :: Python
Classifier: Programming Language :: Python :: 3
Classifier: Programming Language :: Python :: 3 :: Only
Classifier: Programming Language :: Python :: 3.7
Classifier: Programming Language :: Python :: 3.8
Classifier: Programming Language :: Python :: 3.9
Classifier: Programming Language :: Python :: 3.10
Classifier: Programming Language :: Python :: Implementation :: CPython
Classifier: Programming Language :: Python :: Implementation :: PyPy
Classifier: Topic :: Text Processing
Requires-Dist: webencodings >=0.4
Requires-Dist: sphinx ; extra == "doc"
Requires-Dist: sphinx_rtd_theme ; extra == "doc"
Requires-Dist: pytest ; extra == "test"
Requires-Dist: isort ; extra == "test"
Requires-Dist: flake8 ; extra == "test"
Project-URL: Changelog, https://github.com/Kozea/tinycss2/releases
Project-URL: Code, https://github.com/Kozea/tinycss2/
Project-URL: Documentation, https://doc.courtbouillon.org/tinycss2/
Project-URL: Donation, https://opencollective.com/courtbouillon
Project-URL: Homepage, https://www.courtbouillon.org/tinycss2
Project-URL: Issues, https://github.com/Kozea/tinycss2/issues
Provides-Extra: doc
Provides-Extra: test
